{
    "km": 56.58,
    "source": "route",
    "route_provider": "osrm",
    "route_points": [],
    "home_coords": {
        "lat": 2.8027574,
        "lon": 101.4956767,
        "display_name": "Banting, Kuala Langat, Selangor, Malaysia",
        "matched_query": "Banting, 42700, Selangor, Malaysia"
    },
    "office_coords": {
        "lat": 3.052805,
        "lon": 101.7233,
        "display_name": "UNIVERSITI PERTAHANAN NASIONAL MALAYSIA, KEM SUNGAI BESI, 57000 KUALA LUMPUR, WILAYAH PERSEKUTUAN KUALA LUMPUR, MALAYSIA"
    },
    "cached_at": "2026-04-03T21:43:22+00:00"
}