{
    "km": 18.81,
    "source": "route",
    "route_provider": "osrm",
    "route_points": [],
    "home_coords": {
        "lat": 2.969517,
        "lon": 101.6542291,
        "display_name": "Bandar 16 Sierra, Sepang, Selangor, Malaysia",
        "matched_query": "Bandar 16 Sierra, Puchong, 47120, Selangor, Malaysia"
    },
    "office_coords": {
        "lat": 3.052805,
        "lon": 101.7233,
        "display_name": "UNIVERSITI PERTAHANAN NASIONAL MALAYSIA, KEM SUNGAI BESI, 57000 KUALA LUMPUR, WILAYAH PERSEKUTUAN KUALA LUMPUR, MALAYSIA"
    },
    "cached_at": "2026-04-03T23:17:07+00:00"
}