{
    "km": 42.29,
    "source": "route",
    "route_provider": "osrm",
    "route_points": [],
    "home_coords": {
        "lat": 2.8276842,
        "lon": 101.632106,
        "display_name": "Kampung Bukit Changgang, Bukit Changgang, Banting, Kuala Langat, Selangor, 43800, Malaysia",
        "matched_query": "Kampung Bukit Changgang, 42700, Selangor, Malaysia"
    },
    "office_coords": {
        "lat": 3.052805,
        "lon": 101.7233,
        "display_name": "UNIVERSITI PERTAHANAN NASIONAL MALAYSIA, KEM SUNGAI BESI, 57000 KUALA LUMPUR, WILAYAH PERSEKUTUAN KUALA LUMPUR, MALAYSIA"
    },
    "cached_at": "2026-04-03T21:38:48+00:00"
}