{
    "km": 57.76,
    "source": "route",
    "route_provider": "osrm",
    "route_points": [],
    "home_coords": {
        "lat": 3.4385711,
        "lon": 101.6661697,
        "display_name": "Kampung Sungai Kamin (Utara), Jalan Batang Kali - Hulu Yam Bharu, Jalan Batang Kali–Hulu Yam Bharu, Kampung Sungai Kamin, Batang Kali, Hulu Selangor, Selangor, 44300, Malaysia",
        "matched_query": "Kampung Sungai Kamin Ulu Yam Bharu, 44300 Batang Kali, Hulu Selangor, Selangor, Malaysia"
    },
    "office_coords": {
        "lat": 3.052805,
        "lon": 101.7233,
        "display_name": "UNIVERSITI PERTAHANAN NASIONAL MALAYSIA, KEM SUNGAI BESI, 57000 KUALA LUMPUR, WILAYAH PERSEKUTUAN KUALA LUMPUR, MALAYSIA"
    },
    "cached_at": "2026-04-03T22:17:09+00:00"
}