{
    "km": 197.78,
    "source": "route",
    "route_provider": "osrm",
    "route_points": [],
    "home_coords": {
        "lat": 3.268688,
        "lon": 102.6072014,
        "display_name": "FELDA Tementi, Bera, Pahang, 28300, Malaysia",
        "matched_query": "(A1) Felda Tementi, 28200 Bera, Pahang, Malaysia"
    },
    "office_coords": {
        "lat": 3.052805,
        "lon": 101.7233,
        "display_name": "UNIVERSITI PERTAHANAN NASIONAL MALAYSIA, KEM SUNGAI BESI, 57000 KUALA LUMPUR, WILAYAH PERSEKUTUAN KUALA LUMPUR, MALAYSIA"
    },
    "cached_at": "2026-04-03T22:21:12+00:00"
}