{
    "km": 30.32,
    "source": "route",
    "route_provider": "osrm",
    "route_points": [],
    "home_coords": {
        "lat": 3.2205505,
        "lon": 101.6434493,
        "display_name": "Taman Metropolitan Kepong, Jinjang, Kepong, Kuala Lumpur, Malaysia",
        "matched_query": "Taman Metropolitan, Kepong, 52100, Wilayah Persekutuan Kuala Lumpur, Malaysia"
    },
    "office_coords": {
        "lat": 3.052805,
        "lon": 101.7233,
        "display_name": "UNIVERSITI PERTAHANAN NASIONAL MALAYSIA, KEM SUNGAI BESI, 57000 KUALA LUMPUR, WILAYAH PERSEKUTUAN KUALA LUMPUR, MALAYSIA"
    },
    "cached_at": "2026-04-03T23:49:47+00:00"
}