{
    "km": 13.337,
    "provider": "google",
    "points": [
        {
            "lat": 3.11613,
            "lon": 101.76828
        },
        {
            "lat": 3.11557,
            "lon": 101.76845
        },
        {
            "lat": 3.11543,
            "lon": 101.76798
        },
        {
            "lat": 3.11587,
            "lon": 101.76783
        },
        {
            "lat": 3.11598,
            "lon": 101.76776
        },
        {
            "lat": 3.11639,
            "lon": 101.76727
        },
        {
            "lat": 3.11599,
            "lon": 101.76695
        },
        {
            "lat": 3.11522,
            "lon": 101.76637
        },
        {
            "lat": 3.11495,
            "lon": 101.76602
        },
        {
            "lat": 3.11483,
            "lon": 101.76581
        },
        {
            "lat": 3.11434,
            "lon": 101.76466
        },
        {
            "lat": 3.11425,
            "lon": 101.7645
        },
        {
            "lat": 3.11445,
            "lon": 101.76442
        },
        {
            "lat": 3.1145,
            "lon": 101.76443
        },
        {
            "lat": 3.11487,
            "lon": 101.76424
        },
        {
            "lat": 3.1158,
            "lon": 101.76388
        },
        {
            "lat": 3.1146,
            "lon": 101.76036
        },
        {
            "lat": 3.1144,
            "lon": 101.76006
        },
        {
            "lat": 3.11431,
            "lon": 101.75999
        },
        {
            "lat": 3.11427,
            "lon": 101.75988
        },
        {
            "lat": 3.11428,
            "lon": 101.75976
        },
        {
            "lat": 3.11435,
            "lon": 101.75967
        },
        {
            "lat": 3.11436,
            "lon": 101.75966
        },
        {
            "lat": 3.11443,
            "lon": 101.75937
        },
        {
            "lat": 3.11434,
            "lon": 101.75854
        },
        {
            "lat": 3.11435,
            "lon": 101.75837
        },
        {
            "lat": 3.11438,
            "lon": 101.7582
        },
        {
            "lat": 3.11467,
            "lon": 101.75718
        },
        {
            "lat": 3.11478,
            "lon": 101.75687
        },
        {
            "lat": 3.11487,
            "lon": 101.75655
        },
        {
            "lat": 3.1148,
            "lon": 101.75626
        },
        {
            "lat": 3.11402,
            "lon": 101.75594
        },
        {
            "lat": 3.11293,
            "lon": 101.75496
        },
        {
            "lat": 3.11263,
            "lon": 101.75475
        },
        {
            "lat": 3.11137,
            "lon": 101.75396
        },
        {
            "lat": 3.11108,
            "lon": 101.7538
        },
        {
            "lat": 3.11055,
            "lon": 101.75344
        },
        {
            "lat": 3.11018,
            "lon": 101.75324
        },
        {
            "lat": 3.1098,
            "lon": 101.75295
        },
        {
            "lat": 3.10974,
            "lon": 101.75288
        },
        {
            "lat": 3.10955,
            "lon": 101.75261
        },
        {
            "lat": 3.10926,
            "lon": 101.75214
        },
        {
            "lat": 3.10923,
            "lon": 101.752
        },
        {
            "lat": 3.10866,
            "lon": 101.75111
        },
        {
            "lat": 3.10779,
            "lon": 101.74962
        },
        {
            "lat": 3.10688,
            "lon": 101.74817
        },
        {
            "lat": 3.10678,
            "lon": 101.74797
        },
        {
            "lat": 3.1063,
            "lon": 101.74672
        },
        {
            "lat": 3.10628,
            "lon": 101.74654
        },
        {
            "lat": 3.1063,
            "lon": 101.7464
        },
        {
            "lat": 3.10663,
            "lon": 101.74546
        },
        {
            "lat": 3.10679,
            "lon": 101.74512
        },
        {
            "lat": 3.10714,
            "lon": 101.74447
        },
        {
            "lat": 3.10729,
            "lon": 101.74411
        },
        {
            "lat": 3.10736,
            "lon": 101.74378
        },
        {
            "lat": 3.10732,
            "lon": 101.74344
        },
        {
            "lat": 3.10714,
            "lon": 101.74312
        },
        {
            "lat": 3.10691,
            "lon": 101.74285
        },
        {
            "lat": 3.10643,
            "lon": 101.74234
        },
        {
            "lat": 3.10639,
            "lon": 101.74223
        },
        {
            "lat": 3.10638,
            "lon": 101.74218
        },
        {
            "lat": 3.10598,
            "lon": 101.74183
        },
        {
            "lat": 3.10556,
            "lon": 101.74149
        },
        {
            "lat": 3.10552,
            "lon": 101.74141
        },
        {
            "lat": 3.1055,
            "lon": 101.74131
        },
        {
            "lat": 3.10506,
            "lon": 101.74098
        },
        {
            "lat": 3.10466,
            "lon": 101.74073
        },
        {
            "lat": 3.10422,
            "lon": 101.74051
        },
        {
            "lat": 3.10363,
            "lon": 101.74026
        },
        {
            "lat": 3.10331,
            "lon": 101.74016
        },
        {
            "lat": 3.10207,
            "lon": 101.73984
        },
        {
            "lat": 3.10191,
            "lon": 101.73978
        },
        {
            "lat": 3.10142,
            "lon": 101.73954
        },
        {
            "lat": 3.10091,
            "lon": 101.73919
        },
        {
            "lat": 3.10064,
            "lon": 101.73895
        },
        {
            "lat": 3.1004,
            "lon": 101.73869
        },
        {
            "lat": 3.09972,
            "lon": 101.73784
        },
        {
            "lat": 3.09589,
            "lon": 101.733
        },
        {
            "lat": 3.09563,
            "lon": 101.7327
        },
        {
            "lat": 3.09527,
            "lon": 101.73237
        },
        {
            "lat": 3.09494,
            "lon": 101.73211
        },
        {
            "lat": 3.09347,
            "lon": 101.73107
        },
        {
            "lat": 3.09263,
            "lon": 101.73052
        },
        {
            "lat": 3.09207,
            "lon": 101.73022
        },
        {
            "lat": 3.09145,
            "lon": 101.72998
        },
        {
            "lat": 3.0911,
            "lon": 101.72987
        },
        {
            "lat": 3.09057,
            "lon": 101.72975
        },
        {
            "lat": 3.09007,
            "lon": 101.72966
        },
        {
            "lat": 3.08939,
            "lon": 101.7296
        },
        {
            "lat": 3.08679,
            "lon": 101.72958
        },
        {
            "lat": 3.08475,
            "lon": 101.72956
        },
        {
            "lat": 3.08396,
            "lon": 101.72953
        },
        {
            "lat": 3.08359,
            "lon": 101.72948
        },
        {
            "lat": 3.08314,
            "lon": 101.72935
        },
        {
            "lat": 3.08271,
            "lon": 101.72917
        },
        {
            "lat": 3.0823,
            "lon": 101.72894
        },
        {
            "lat": 3.08191,
            "lon": 101.72864
        },
        {
            "lat": 3.08178,
            "lon": 101.72853
        },
        {
            "lat": 3.08141,
            "lon": 101.72812
        },
        {
            "lat": 3.08123,
            "lon": 101.72787
        },
        {
            "lat": 3.08102,
            "lon": 101.7275
        },
        {
            "lat": 3.08086,
            "lon": 101.72715
        },
        {
            "lat": 3.08073,
            "lon": 101.72669
        },
        {
            "lat": 3.07994,
            "lon": 101.72272
        },
        {
            "lat": 3.07988,
            "lon": 101.72223
        },
        {
            "lat": 3.07976,
            "lon": 101.72047
        },
        {
            "lat": 3.07971,
            "lon": 101.72027
        },
        {
            "lat": 3.07957,
            "lon": 101.71995
        },
        {
            "lat": 3.07936,
            "lon": 101.71961
        },
        {
            "lat": 3.0789,
            "lon": 101.71874
        },
        {
            "lat": 3.07856,
            "lon": 101.71821
        },
        {
            "lat": 3.07842,
            "lon": 101.71788
        },
        {
            "lat": 3.078,
            "lon": 101.71719
        },
        {
            "lat": 3.07764,
            "lon": 101.71664
        },
        {
            "lat": 3.07755,
            "lon": 101.71651
        },
        {
            "lat": 3.07721,
            "lon": 101.71609
        },
        {
            "lat": 3.07657,
            "lon": 101.71497
        },
        {
            "lat": 3.07605,
            "lon": 101.71391
        },
        {
            "lat": 3.07536,
            "lon": 101.71255
        },
        {
            "lat": 3.07512,
            "lon": 101.71207
        },
        {
            "lat": 3.07489,
            "lon": 101.71171
        },
        {
            "lat": 3.07446,
            "lon": 101.71118
        },
        {
            "lat": 3.07369,
            "lon": 101.71028
        },
        {
            "lat": 3.07347,
            "lon": 101.71006
        },
        {
            "lat": 3.07319,
            "lon": 101.70986
        },
        {
            "lat": 3.07295,
            "lon": 101.70972
        },
        {
            "lat": 3.07253,
            "lon": 101.70954
        },
        {
            "lat": 3.07213,
            "lon": 101.70945
        },
        {
            "lat": 3.07099,
            "lon": 101.70927
        },
        {
            "lat": 3.07022,
            "lon": 101.70922
        },
        {
            "lat": 3.06945,
            "lon": 101.70924
        },
        {
            "lat": 3.06869,
            "lon": 101.70933
        },
        {
            "lat": 3.06817,
            "lon": 101.7094
        },
        {
            "lat": 3.0679,
            "lon": 101.70941
        },
        {
            "lat": 3.06753,
            "lon": 101.70933
        },
        {
            "lat": 3.06736,
            "lon": 101.70927
        },
        {
            "lat": 3.06715,
            "lon": 101.70925
        },
        {
            "lat": 3.06688,
            "lon": 101.70911
        },
        {
            "lat": 3.06637,
            "lon": 101.70867
        },
        {
            "lat": 3.0662,
            "lon": 101.70858
        },
        {
            "lat": 3.06599,
            "lon": 101.70853
        },
        {
            "lat": 3.06581,
            "lon": 101.70853
        },
        {
            "lat": 3.06568,
            "lon": 101.70855
        },
        {
            "lat": 3.06525,
            "lon": 101.70855
        },
        {
            "lat": 3.06475,
            "lon": 101.70849
        },
        {
            "lat": 3.0647,
            "lon": 101.70861
        },
        {
            "lat": 3.06451,
            "lon": 101.70939
        },
        {
            "lat": 3.06439,
            "lon": 101.70965
        },
        {
            "lat": 3.06429,
            "lon": 101.70982
        },
        {
            "lat": 3.06422,
            "lon": 101.70991
        },
        {
            "lat": 3.06399,
            "lon": 101.7101
        },
        {
            "lat": 3.06439,
            "lon": 101.71059
        },
        {
            "lat": 3.06411,
            "lon": 101.71084
        },
        {
            "lat": 3.06454,
            "lon": 101.71136
        },
        {
            "lat": 3.06525,
            "lon": 101.71229
        },
        {
            "lat": 3.06527,
            "lon": 101.71237
        },
        {
            "lat": 3.06543,
            "lon": 101.71265
        },
        {
            "lat": 3.06489,
            "lon": 101.71303
        },
        {
            "lat": 3.06446,
            "lon": 101.71326
        },
        {
            "lat": 3.06434,
            "lon": 101.71338
        },
        {
            "lat": 3.06425,
            "lon": 101.71353
        },
        {
            "lat": 3.06415,
            "lon": 101.7138
        },
        {
            "lat": 3.06398,
            "lon": 101.71469
        },
        {
            "lat": 3.0639,
            "lon": 101.71502
        },
        {
            "lat": 3.0638,
            "lon": 101.7152
        },
        {
            "lat": 3.06348,
            "lon": 101.71552
        },
        {
            "lat": 3.06322,
            "lon": 101.71572
        },
        {
            "lat": 3.06306,
            "lon": 101.7158
        },
        {
            "lat": 3.06259,
            "lon": 101.71593
        },
        {
            "lat": 3.06069,
            "lon": 101.71651
        },
        {
            "lat": 3.05965,
            "lon": 101.71685
        },
        {
            "lat": 3.05936,
            "lon": 101.71692
        },
        {
            "lat": 3.05927,
            "lon": 101.71851
        },
        {
            "lat": 3.05926,
            "lon": 101.71862
        },
        {
            "lat": 3.05935,
            "lon": 101.71866
        },
        {
            "lat": 3.0594,
            "lon": 101.71875
        },
        {
            "lat": 3.05939,
            "lon": 101.71884
        },
        {
            "lat": 3.05931,
            "lon": 101.71891
        },
        {
            "lat": 3.05923,
            "lon": 101.71893
        },
        {
            "lat": 3.0591,
            "lon": 101.72148
        },
        {
            "lat": 3.05903,
            "lon": 101.72265
        },
        {
            "lat": 3.059,
            "lon": 101.72327
        },
        {
            "lat": 3.05909,
            "lon": 101.72331
        },
        {
            "lat": 3.05914,
            "lon": 101.72339
        },
        {
            "lat": 3.05913,
            "lon": 101.7235
        },
        {
            "lat": 3.05906,
            "lon": 101.72357
        },
        {
            "lat": 3.05897,
            "lon": 101.72358
        },
        {
            "lat": 3.05888,
            "lon": 101.72354
        },
        {
            "lat": 3.05883,
            "lon": 101.72345
        },
        {
            "lat": 3.05704,
            "lon": 101.72356
        },
        {
            "lat": 3.0546,
            "lon": 101.72375
        },
        {
            "lat": 3.05418,
            "lon": 101.72373
        },
        {
            "lat": 3.05363,
            "lon": 101.72363
        },
        {
            "lat": 3.05278,
            "lon": 101.72342
        }
    ]
}